inlinestyler/__init__.py
inlinestyler/converter.py
inlinestyler/css_compliance.csv
inlinestyler/cssselect.py
inlinestyler/utils.py
inlinestyler-0.2.5.dist-info/DESCRIPTION.rst
inlinestyler-0.2.5.dist-info/METADATA
inlinestyler-0.2.5.dist-info/RECORD
inlinestyler-0.2.5.dist-info/WHEEL
inlinestyler-0.2.5.dist-info/metadata.json
inlinestyler-0.2.5.dist-info/top_level.txt
