Metadata-Version: 1.2
Name: inlinestyler
Version: 0.2.5
Summary: Inlines external CSS into HTML elements.
Home-page: http://github.com/dlanger/inlinestyler
Author: Dave Cranwell
Maintainer: Dan Langer
Maintainer-email: daniel@langer.me
License: BSD
Download-URL: http://github.com/dlanger/inlinestyler/downloads
Keywords: html,css,inline,style,email
Platform: UNKNOWN
Classifier: Development Status :: 5 - Production/Stable
Classifier: Environment :: Other Environment
Classifier: Environment :: Web Environment
Classifier: Intended Audience :: Developers
Classifier: License :: OSI Approved :: BSD License
Classifier: Operating System :: OS Independent
Classifier: Programming Language :: Python :: 2.6
Classifier: Programming Language :: Python :: 2.7
Classifier: Programming Language :: Python :: 3.2
Classifier: Programming Language :: Python :: 3.4
Classifier: Topic :: Communications :: Email
Classifier: Topic :: Text Processing :: Markup :: HTML
